docstats/__init__.py
docstats/directives/call_graph.py
docstats-0.1.2.dist-info/LICENSE
docstats-0.1.2.dist-info/WHEEL
docstats-0.1.2.dist-info/METADATA
docstats-0.1.2.dist-info/RECORD
