Metadata-Version: 2.1
Name: docstats
Version: 0.1.2
Summary: Statistics and other numbers for your sphinx pages
License: MIT
Author: GameDungeon
Author-email: gamedungeon@protonmail.com
Requires-Python: >=3.7,<4.0
Classifier: License :: OSI Approved :: MIT License
Classifier: Programming Language :: Python :: 3
Classifier: Programming Language :: Python :: 3.10
Classifier: Programming Language :: Python :: 3.7
Classifier: Programming Language :: Python :: 3.8
Classifier: Programming Language :: Python :: 3.9
Requires-Dist: Sphinx (>=4.3.2,<5.0.0)
